yandex_realty_parser/__init__.py
yandex_realty_parser/yandex_realty_parser.py
yandex_realty_parser-0.2.0.dist-info/LICENSE
yandex_realty_parser-0.2.0.dist-info/METADATA
yandex_realty_parser-0.2.0.dist-info/WHEEL
yandex_realty_parser-0.2.0.dist-info/top_level.txt
yandex_realty_parser-0.2.0.dist-info/RECORD
