Metadata-Version: 2.1
Name: yandex-realty-parser
Version: 0.2.0
Summary: Library that parses yandex realty website
Author-email: Dmitriy Gorokhov <didedoshka@gmail.com>
License: MIT License
Keywords: realty,parse
Requires-Python: >=3.7
License-File: LICENSE
